odoo/addons/cms_delete_content/README.rst
odoo/addons/cms_delete_content/__init__.py
odoo/addons/cms_delete_content/__manifest__.py
odoo/addons/cms_delete_content/controllers/__init__.py
odoo/addons/cms_delete_content/controllers/main.py
odoo/addons/cms_delete_content/i18n/ca.po
odoo/addons/cms_delete_content/i18n/cms_delete_content.pot
odoo/addons/cms_delete_content/i18n/de.po
odoo/addons/cms_delete_content/i18n/es.po
odoo/addons/cms_delete_content/models/__init__.py
odoo/addons/cms_delete_content/models/cms_mixin.py
odoo/addons/cms_delete_content/readme/CONTRIBUTORS.rst
odoo/addons/cms_delete_content/readme/DESCRIPTION.rst
odoo/addons/cms_delete_content/readme/HISTORY.rst
odoo/addons/cms_delete_content/readme/ROADMAP.rst
odoo/addons/cms_delete_content/readme/USAGE.rst
odoo/addons/cms_delete_content/static/description/icon.png
odoo/addons/cms_delete_content/static/description/index.html
odoo/addons/cms_delete_content/static/src/js/delete_content.js
odoo/addons/cms_delete_content/templates/assets.xml
odoo/addons/cms_delete_content/templates/delete_confirm.xml
odoo/addons/cms_delete_content/tests/__init__.py
odoo/addons/cms_delete_content/tests/fake_models.py
odoo/addons/cms_delete_content/tests/test_delete.py
odoo13_addon_cms_delete_content-13.0.1.0.1.dist-info/METADATA
odoo13_addon_cms_delete_content-13.0.1.0.1.dist-info/WHEEL
odoo13_addon_cms_delete_content-13.0.1.0.1.dist-info/top_level.txt
odoo13_addon_cms_delete_content-13.0.1.0.1.dist-info/RECORD
