Metadata-Version: 2.1
Name: odoo13-addon-cms-delete-content
Version: 13.0.1.0.1
Summary: Basic features for handling content deletion via frontend.
Home-page: https://github.com/OCA/website-cms
Author: Camptocamp,Odoo Community Association (OCA)
Author-email: support@odoo-community.org
License: LGPL-3
Platform: UNKNOWN
Classifier: Programming Language :: Python
Classifier: Framework :: Odoo
Classifier: License :: OSI Approved :: GNU Lesser General Public License v3 (LGPLv3)
Requires-Python: >=3.5
Requires-Dist: odoo13-addon-cms-info
Requires-Dist: odoo13-addon-cms-status-message
Requires-Dist: odoo (<13.1dev,>=13.0a)
